jaxtyping/__init__.py
jaxtyping/_array_types.py
jaxtyping/_decorator.py
jaxtyping/_import_hook.py
jaxtyping/_indirection.py
jaxtyping/_pytest_plugin.py
jaxtyping/_pytree_type.py
jaxtyping/py.typed
ezjaxtyping-0.2.20.dist-info/METADATA
ezjaxtyping-0.2.20.dist-info/WHEEL
ezjaxtyping-0.2.20.dist-info/entry_points.txt
ezjaxtyping-0.2.20.dist-info/licenses/LICENSE
ezjaxtyping-0.2.20.dist-info/RECORD
