Metadata-Version: 2.1
Name: ezjaxtyping
Version: 0.2.20
Summary: Type annotations and runtime checking for shape and dtype of JAX arrays, and PyTrees.
Project-URL: repository, https://github.com/ezhang7423/relaxed-jaxtyping
Author-email: Eddie Zhang <futzipecinematography@gmail.com>
License: MIT License
License-File: LICENSE
Keywords: deep-learning,equinox,jax,neural-networks,typing
Classifier: Development Status :: 3 - Alpha
Classifier: Intended Audience :: Developers
Classifier: Intended Audience :: Financial and Insurance Industry
Classifier: Intended Audience :: Information Technology
Classifier: Intended Audience :: Science/Research
Classifier: License :: OSI Approved :: MIT License
Classifier: Natural Language :: English
Classifier: Programming Language :: Python :: 3
Classifier: Topic :: Scientific/Engineering :: Artificial Intelligence
Classifier: Topic :: Scientific/Engineering :: Information Analysis
Classifier: Topic :: Scientific/Engineering :: Mathematics
Requires-Python: ~=3.8
Requires-Dist: numpy>=1.20.0
Requires-Dist: typeguard>=2.13.3
Requires-Dist: typing-extensions>=3.7.4.1
